{
    "id": "A1/87",
    "name": "Froakie",
    "entry": 87,
    "rarity": 1,
    "source": "Charizard Pack",
    "image": "https://limitlesstcg.nyc3.cdn.digitaloceanspaces.com/pocket/A1/A1_087_EN.webp",
    "layout": "Pokemon",
    "type": "Water",
    "hp": 60,
    "stage": "Basic",
    "weakness": "Lightning",
    "retreat": 1,
    "has_ability": false,
    "moves": [
        {
            "name": "Flop",
            "damage": "10",
            "cost": "Colorless",
            "effect": ""
        }
    ],
    "is_ex": false,
    "versions": []
}