{
    "id": "A1/92",
    "entry": 92,
    "source": "All Packs",
    "rarity": 1,
    "layout": "Pokemon",
    "name": "Snom",
    "type": "Water",
    "hp": 50,
    "stage": "Basic",
    "weakness": "Metal",
    "retreat": 1,
    "has_ability": false,
    "moves": [
        {
            "name": "Ram",
            "damage": "10",
            "cost": "Colorless",
            "effect": ""
        }
    ],
    "is_ex": false,
    "image": "https://limitlesstcg.nyc3.cdn.digitaloceanspaces.com/pocket/A1/A1_092_EN.webp",
    "versions": []
}