{
    "id": "A1/104",
    "name": "Zapdos ex",
    "entry": 104,
    "rarity": 4,
    "source": "Pikachu Pack",
    "image": "https://limitlesstcg.nyc3.cdn.digitaloceanspaces.com/pocket/A1/A1_104_EN.webp",
    "layout": "Pokemon",
    "type": "Lightning",
    "hp": 130,
    "stage": "Basic",
    "weakness": "Lightning",
    "retreat": 1,
    "has_ability": false,
    "moves": [
        {
            "name": "Peck",
            "damage": "20",
            "cost": "Lightning",
            "effect": ""
        },
        {
            "name": "Thundering Hurricane",
            "damage": "50x",
            "cost": "Lightning Lightning Lightning",
            "effect": "Flip 4 coins. This attack does 50 damage for each heads."
        }
    ],
    "is_ex": true,
    "versions": [
        "A1/260",
        "A1/276"
    ]
}