{
    "id": "A1/127",
    "name": "Jynx",
    "entry": 127,
    "rarity": 1,
    "source": "Mewtwo Pack",
    "image": "https://limitlesstcg.nyc3.cdn.digitaloceanspaces.com/pocket/A1/A1_127_EN.webp",
    "layout": "Pokemon",
    "type": "Psychic",
    "hp": 80,
    "stage": "Basic",
    "weakness": "Darkness",
    "retreat": 1,
    "has_ability": false,
    "moves": [
        {
            "name": "Psychic",
            "damage": "30+",
            "cost": "Psychic Colorless",
            "effect": "This attack does 20 more damage for each Energy attached to your opponent's Active Pokemon."
        }
    ],
    "is_ex": false,
    "versions": []
}