{
    "id": "A1/246",
    "name": "Meowth",
    "entry": 246,
    "rarity": 5,
    "source": "Charizard Pack",
    "image": "https://limitlesstcg.nyc3.cdn.digitaloceanspaces.com/pocket/A1/A1_246_EN.webp",
    "layout": "Pokemon",
    "type": "Colorless",
    "hp": 60,
    "stage": "Basic",
    "weakness": "Fighting",
    "retreat": 1,
    "has_ability": false,
    "moves": [
        {
            "name": "Pay Day",
            "damage": "10",
            "cost": "Colorless",
            "effect": "Draw 1 card."
        }
    ],
    "is_ex": false,
    "versions": [
        "A1/196",
        "P-A/12"
    ]
}